docs/user-guide/commands/check-deck.md
docs/user-guide/commands/print-deck.md
sarar/click_utils.py
sarar/commands/check_deck.py
sarar/commands/print_deck.py
sarar/decorators.py
sarar/sarar.py
sarar-0.1.0.dist-info/entry_points.txt
sarar-0.1.0.dist-info/LICENSE.md
sarar-0.1.0.dist-info/WHEEL
sarar-0.1.0.dist-info/METADATA
sarar-0.1.0.dist-info/RECORD
