Metadata-Version: 2.1
Name: sarar
Version: 0.1.0
Summary: SARAR is a command-line-interface tool for GNU/Linux, its goal is to optimize the process of remembering things.
License: GNU GPLv3
Author: Stéphane Tzvetkov
Requires-Python: >=3.8,<4.0
Classifier: License :: Other/Proprietary License
Classifier: Programming Language :: Python :: 3
Classifier: Programming Language :: Python :: 3.8
Classifier: Programming Language :: Python :: 3.9
Requires-Dist: asteval (>=0.9.23,<0.10.0)
Requires-Dist: click (>=7.1.2,<8.0.0)
Requires-Dist: pycron (>=3.0.0,<4.0.0)
Requires-Dist: ruamel.yaml (>=0.16.13,<0.17.0)
Requires-Dist: typeguard (>=2.12.0,<3.0.0)
